Workbook
Name Aporte: Simulador!$E$22
Name Patrimonio: Simulador!$E$25
Name QTD_Anos: Simulador!$E$24
Name Rendimento_carteira: Simulador!$E$16
Name Salario: Simulador!$E$15
Name Sugestão_Investimento: Simulador!$E$17
Name Taxa_mensal: Simulador!$E$23

Sheet Simulador
D15: Salário | E15: 300
D16: Rendimento da carteira | E16: 0.01
D17: Sugestão de Investimento (30%) | E17: =E15*30% -> 90
C21: 2
C22: 5 | D22: Informe quanto desejar investir por mês? | E22: 60
C23: 10 | D23: Informe aTaxa de rendimento mensal? | E23: 0.01
C24: 15 | D24: Informe Por quantos anos pretende investir? | E24: 2
C25: 20 | D25: Qual patrimônio acumulado | E25: =FV(Taxa_mensal,QTD_Anos*12,Aporte*-1) -> 1618.4079
C26: 30 | D26: Dividendo mensais | E26: =E25*$E$16 -> 16.184079
D29: CENÁRIOS | F29: DIVIDENDO
D30: Quanto em 02 anos? | E30: =FV($E$23,$C21*12,$E$22*-1) -> 1618.4079 | F30: =E30*$E$16 -> 16.184079
D31: Quanto em 05 anos? | E31: =FV($E$23,$C22*12,$E$22*-1) -> 4900.1802 | F31: =E31*$E$16 -> 49.001802
D32: Quanto em 10 anos? | E32: =FV($E$23,$C23*12,$E$22*-1) -> 13802.321 | F32: =E32*$E$16 -> 138.02321
D33: Quanto em 15 anos? | E33: =FV($E$23,$C24*12,$E$22*-1) -> 29974.812 | F33: =E33*$E$16 -> 299.74812
D34: Quanto em 20 anos? | E34: =FV($E$23,$C25*12,$E$22*-1) -> 59355.322 | F34: =E34*$E$16 -> 593.55322
D35: Quanto em 30 anos? | E35: =FV($E$23,$C26*12,$E$22*-1) -> 209697.85 | F35: =E35*$E$16 -> 2096.9785
D40: CONSERVADOR
D41: VALOR MENSAL DE INVESTIMENTO: | E41: 60
D43: Tipo de FII | E43: % Sugerido | F43: Valores
D44: PAPEL | E44: =VLOOKUP($D$40&"-"&D44,Planilha1!$A:$D,4,) -> 0.3 | F44: =E44*$E$41 -> 18
D45: TIJOLO | E45: =VLOOKUP($D$40&"-"&D45,Planilha1!$A:$D,4,) -> 0.5 | F45: =E45*$E$41 -> 30
D46: HIBRÍDOS | E46: =VLOOKUP($D$40&"-"&D46,Planilha1!$A:$D,4,) -> 0.1 | F46: =E46*$E$41 -> 6
D47: FOFS | E47: =VLOOKUP($D$40&"-"&D47,Planilha1!$A:$D,4,) -> 0.1 | F47: =E47*$E$41 -> 6
D48: DESENVOLVIMENTO | E48: =VLOOKUP($D$40&"-"&D48,Planilha1!$A:$D,4,) -> 0 | F48: =E48*$E$41 -> 0
D49: HOTELARIA | E49: =VLOOKUP($D$40&"-"&D49,Planilha1!$A:$D,4,) -> 0 | F49: =E49*$E$41 -> 0
D50: TOTAL | F50: =SUM(F44:F49) -> 60

Sheet Planilha1
A3: CHAVE | B3: PERFIL | C3: TIPO | D3: %
A4: =$B$4&"-"&C4 -> CONSERVADOR-PAPEL | B4: CONSERVADOR | C4: PAPEL | D4: 0.3
A5: =$B$4&"-"&C5 -> CONSERVADOR-TIJOLO | B5: CONSERVADOR | C5: TIJOLO | D5: 0.5
A6: =$B$4&"-"&C6 -> CONSERVADOR-HIBRÍDOS | B6: CONSERVADOR | C6: HIBRÍDOS | D6: 0.1
A7: =$B$4&"-"&C7 -> CONSERVADOR-FOFS | B7: CONSERVADOR | C7: FOFS | D7: 0.1
A8: =$B$4&"-"&C8 -> CONSERVADOR-DESENVOLVIMENTO | B8: CONSERVADOR | C8: DESENVOLVIMENTO | D8: 0
A9: =$B$4&"-"&C9 -> CONSERVADOR-HOTELARIA | B9: CONSERVADOR | C9: HOTELARIA | D9: 0
A10: =$B$10&"-"&C10 -> MODERADO-TIPO | B10: MODERADO | C10: TIPO | D10: %
A11: =$B$10&"-"&C11 -> MODERADO-PAPEL | B11: MODERADO | C11: PAPEL | D11: 0.32
A12: =$B$10&"-"&C12 -> MODERADO-TIJOLO | B12: MODERADO | C12: TIJOLO | D12: 0.35
A13: =$B$10&"-"&C13 -> MODERADO-HIBRÍDOS | B13: MODERADO | C13: HIBRÍDOS | D13: 0.08
A14: =$B$10&"-"&C14 -> MODERADO-FOFS | B14: MODERADO | C14: FOFS | D14: 0.05
A15: =$B$10&"-"&C15 -> MODERADO-DESENVOLVIMENTO | B15: MODERADO | C15: DESENVOLVIMENTO | D15: 0.1
A16: =$B$10&"-"&C16 -> MODERADO-HOTELARIA | B16: MODERADO | C16: HOTELARIA | D16: 0.1
A17: =$B$17&"-"&C17 -> AGRESSIVO-TIPO | B17: AGRESSIVO | C17: TIPO | D17: %
A18: =$B$17&"-"&C18 -> AGRESSIVO-PAPEL | B18: AGRESSIVO | C18: PAPEL | D18: 0.5
A19: =$B$17&"-"&C19 -> AGRESSIVO-TIJOLO | B19: AGRESSIVO | C19: TIJOLO | D19: 0.1
A20: =$B$17&"-"&C20 -> AGRESSIVO-HIBRÍDOS | B20: AGRESSIVO | C20: HIBRÍDOS | D20: 0.05
A21: =$B$17&"-"&C21 -> AGRESSIVO-FOFS | B21: AGRESSIVO | C21: FOFS | D21: 0.05
A22: =$B$17&"-"&C22 -> AGRESSIVO-DESENVOLVIMENTO | B22: AGRESSIVO | C22: DESENVOLVIMENTO | D22: 0.2
A23: =$B$17&"-"&C23 -> AGRESSIVO-HOTELARIA | B23: AGRESSIVO | C23: HOTELARIA | D23: 0.1
